invokeai/app/__init__.py
invokeai/app/api_app.py
invokeai/app/run_app.py
invokeai/app/api/dependencies.py
invokeai/app/api/extract_metadata_from_image.py
invokeai/app/api/no_cache_staticfiles.py
invokeai/app/api/sockets.py
invokeai/app/api/routers/app_info.py
invokeai/app/api/routers/board_images.py
invokeai/app/api/routers/boards.py
invokeai/app/api/routers/download_queue.py
invokeai/app/api/routers/images.py
invokeai/app/api/routers/model_manager.py
invokeai/app/api/routers/model_relationships.py
invokeai/app/api/routers/session_queue.py
invokeai/app/api/routers/style_presets.py
invokeai/app/api/routers/utilities.py
invokeai/app/api/routers/workflows.py
invokeai/app/assets/images/caution.png
invokeai/app/invocations/__init__.py
invokeai/app/invocations/baseinvocation.py
invokeai/app/invocations/batch.py
invokeai/app/invocations/blend_latents.py
invokeai/app/invocations/canny.py
invokeai/app/invocations/cogview4_denoise.py
invokeai/app/invocations/cogview4_image_to_latents.py
invokeai/app/invocations/cogview4_latents_to_image.py
invokeai/app/invocations/cogview4_model_loader.py
invokeai/app/invocations/cogview4_text_encoder.py
invokeai/app/invocations/collections.py
invokeai/app/invocations/color_map.py
invokeai/app/invocations/compel.py
invokeai/app/invocations/composition-nodes.py
invokeai/app/invocations/constants.py
invokeai/app/invocations/content_shuffle.py
invokeai/app/invocations/controlnet.py
invokeai/app/invocations/create_denoise_mask.py
invokeai/app/invocations/create_gradient_mask.py
invokeai/app/invocations/crop_latents.py
invokeai/app/invocations/cv.py
invokeai/app/invocations/denoise_latents.py
invokeai/app/invocations/depth_anything.py
invokeai/app/invocations/dw_openpose.py
invokeai/app/invocations/facetools.py
invokeai/app/invocations/fields.py
invokeai/app/invocations/flux_control_lora_loader.py
invokeai/app/invocations/flux_controlnet.py
invokeai/app/invocations/flux_denoise.py
invokeai/app/invocations/flux_fill.py
wowhai-6.1.0.dist-info/licenses/LICENSE
wowhai-6.1.0.dist-info/licenses/LICENSE-SD1+SD2.txt
wowhai-6.1.0.dist-info/licenses/LICENSE-SDXL.txt
wowhai-6.1.0.dist-info/METADATA
wowhai-6.1.0.dist-info/WHEEL
wowhai-6.1.0.dist-info/entry_points.txt
wowhai-6.1.0.dist-info/top_level.txt
wowhai-6.1.0.dist-info/RECORD
